practiceBMItest/BMI module.py
practiceBMItest/BMImodule.py
practiceBMItest-0.0.0.2.dist-info/METADATA
practiceBMItest-0.0.0.2.dist-info/WHEEL
practiceBMItest-0.0.0.2.dist-info/top_level.txt
practiceBMItest-0.0.0.2.dist-info/RECORD
