Metadata-Version: 2.1
Name: practiceBMItest
Version: 0.0.0.2
Summary: Practice BMI test and upload
Home-page: https://blog.naver.com/rkdthfqls7
Author: Martin Kang
Author-email: kangsb1518@gmail.com
License: MIT
Platform: UNKNOWN
Requires-Python: >=3
